CHANGELOG.md
MANIFEST.in
README.rst
requirements.txt
setup.py
src/service/__init__.py
src/service.egg-info/PKG-INFO
src/service.egg-info/SOURCES.txt
src/service.egg-info/dependency_links.txt
src/service.egg-info/requires.txt
src/service.egg-info/top_level.txt
test/test_service.py